argparse_formatter/__init__.py
argparse_formatter/paragraph_formatter.py
argparse_formatter-1.5.dist-info/licenses/LICENSE
argparse_formatter-1.5.dist-info/METADATA
argparse_formatter-1.5.dist-info/WHEEL
argparse_formatter-1.5.dist-info/top_level.txt
argparse_formatter-1.5.dist-info/RECORD
