Metadata-Version: 2.4
Name: argparse_formatter
Version: 1.5
Summary: Paragraph-preserving formatter for argparse
Home-page: https://github.com/davesteele/argparse_formatter
Author: David Steele
Author-email: dsteele@gmail.com
License: GPL 2.0
Classifier: Development Status :: 5 - Production/Stable
Classifier: Intended Audience :: Developers
Classifier: Environment :: Console
Classifier: License :: OSI Approved :: GNU General Public License v2 or later (GPLv2+)
Classifier: Natural Language :: English
Classifier: Operating System :: POSIX :: Linux
Classifier: Operating System :: MacOS
Classifier: Operating System :: Microsoft :: Windows
Classifier: Programming Language :: Python :: 3 :: Only
Classifier: Topic :: Software Development :: User Interfaces
License-File: LICENSE
Dynamic: author
Dynamic: author-email
Dynamic: classifier
Dynamic: description
Dynamic: description-content-type
Dynamic: home-page
Dynamic: license
Dynamic: license-file
Dynamic: summary
